configs/__init__.py
configs/montages.yaml
autoclean/__init__.py
autoclean/__main__.py
autoclean/cli.py
autoclean/calc/assr_analysis.py
autoclean/calc/assr_runner.py
autoclean/calc/assr_viz.py
autoclean/calc/source.py
autoclean/core/__init__.py
autoclean/core/pipeline.py
autoclean/core/task.py
autoclean/io/__init__.py
autoclean/io/export.py
autoclean/io/import_.py
autoclean/mixins/__init__.py
autoclean/mixins/base.py
autoclean/mixins/signal_processing/__init__.py
autoclean/mixins/signal_processing/artifacts.py
autoclean/mixins/signal_processing/autoreject_epochs.py
autoclean/mixins/signal_processing/basic_steps.py
autoclean/mixins/signal_processing/channels.py
autoclean/mixins/signal_processing/eventid_epochs.py
autoclean/mixins/signal_processing/gfp_clean_epochs.py
autoclean/mixins/signal_processing/ica.py
autoclean/mixins/signal_processing/outlier_detection.py
autoclean/mixins/signal_processing/regular_epochs.py
autoclean/mixins/signal_processing/segment_rejection.py
autoclean/mixins/signal_processing/statistical_learning_epochs.py
autoclean/mixins/utils/__init__.py
autoclean/mixins/utils/bids.py
autoclean/mixins/viz/README.md
autoclean/mixins/viz/__init__.py
autoclean/mixins/viz/ica.py
autoclean/mixins/viz/visualization.py
autoclean/plugins/__init__.py
autoclean/plugins/eeg_plugins/__init__.py
autoclean/plugins/eeg_plugins/eeglab_gsn124_plugin.py
autoclean/plugins/eeg_plugins/eeglab_gsn129_plugin.py
autoclean/plugins/eeg_plugins/eeglab_mea30_plugin.py
autoclean/plugins/eeg_plugins/eeglab_standard1020_plugin.py
autoclean/plugins/eeg_plugins/egi_raw_gsn124_plugin.py
autoclean/plugins/eeg_plugins/egi_raw_gsn129_plugin.py
autoclean/plugins/event_processors/README.md
autoclean/plugins/event_processors/__init__.py
autoclean/plugins/event_processors/hbcd_processor.py
autoclean/plugins/event_processors/p300.py
autoclean/plugins/event_processors/resting_state.py
autoclean/plugins/formats/__init__.py
autoclean/plugins/formats/additional_formats.py
autoclean_eeg-2.0.4.dist-info/METADATA
autoclean_eeg-2.0.4.dist-info/WHEEL
autoclean_eeg-2.0.4.dist-info/entry_points.txt
autoclean_eeg-2.0.4.dist-info/licenses/LICENSE
autoclean_eeg-2.0.4.dist-info/RECORD
